Metadata-Version: 2.4
Name: pkn-ccflow
Version: 0.4.2
Summary: My Pocket Knife
Project-URL: Repository, https://github.com/1kbgz/pkn
Project-URL: Homepage, https://github.com/1kbgz/pkn
Author-email: the pkn authors <t.paine154@gmail.com>
License: Apache-2.0
License-File: LICENSE
Classifier: Development Status :: 3 - Alpha
Classifier: Programming Language :: Python
Classifier: Programming Language :: Python :: 3
Classifier: Programming Language :: Python :: 3.10
Classifier: Programming Language :: Python :: 3.11
Classifier: Programming Language :: Python :: 3.12
Classifier: Programming Language :: Python :: 3.13
Classifier: Programming Language :: Python :: 3.14
Classifier: Programming Language :: Python :: Implementation :: CPython
Classifier: Programming Language :: Python :: Implementation :: PyPy
Requires-Python: >=3.10
Requires-Dist: boto3
Requires-Dist: botocore
Requires-Dist: ccflow-email
Requires-Dist: ccflow-s3
Requires-Dist: ccflow>=0.6.10
Requires-Dist: jinja2
Provides-Extra: all
Requires-Dist: boto3; extra == 'all'
Requires-Dist: botocore; extra == 'all'
Requires-Dist: ccflow-email; extra == 'all'
Requires-Dist: ccflow-s3; extra == 'all'
Requires-Dist: ccflow>=0.6.10; extra == 'all'
Requires-Dist: colorlog; extra == 'all'
Requires-Dist: jinja2; extra == 'all'
Requires-Dist: pydantic; extra == 'all'
Provides-Extra: base
Requires-Dist: ccflow-email; extra == 'base'
Requires-Dist: ccflow-s3; extra == 'base'
Requires-Dist: ccflow>=0.6.10; extra == 'base'
Requires-Dist: colorlog; extra == 'base'
Requires-Dist: pydantic; extra == 'base'
Provides-Extra: develop
Requires-Dist: boto3; extra == 'develop'
Requires-Dist: botocore; extra == 'develop'
Requires-Dist: build; extra == 'develop'
Requires-Dist: bump-my-version; extra == 'develop'
Requires-Dist: ccflow-email; extra == 'develop'
Requires-Dist: ccflow-s3; extra == 'develop'
Requires-Dist: ccflow>=0.6.10; extra == 'develop'
Requires-Dist: check-manifest; extra == 'develop'
Requires-Dist: codespell<2.5,>=2.4; extra == 'develop'
Requires-Dist: colorlog; extra == 'develop'
Requires-Dist: emails; extra == 'develop'
Requires-Dist: hatch-multi; extra == 'develop'
Requires-Dist: hatchling; extra == 'develop'
Requires-Dist: jinja2; extra == 'develop'
Requires-Dist: mdformat-tables>=1; extra == 'develop'
Requires-Dist: mdformat<1.1,>=0.7.22; extra == 'develop'
Requires-Dist: pydantic; extra == 'develop'
Requires-Dist: pytest; extra == 'develop'
Requires-Dist: pytest-cov; extra == 'develop'
Requires-Dist: ruff<0.15,>=0.9; extra == 'develop'
Requires-Dist: twine; extra == 'develop'
Requires-Dist: uv; extra == 'develop'
Requires-Dist: wheel; extra == 'develop'
Provides-Extra: logging
